{
    "documents": [
        {
            "name": "projects/the-hidden-inn/databases/(default)/documents/oddUsers/VD99fnrY8FJ3IY7vBErd",
            "fields": {
                "firstname": {
                    "stringValue": "Gregg"
                },
                "emailAddress": {
                    "stringValue": "gregg@gmail.com"
                },
                "address": {
                    "mapValue": {
                        "fields": {
                            "city": {
                                "stringValue": "West Side"
                            },
                            "zipCode": {
                                "stringValue": "01234"
                            },
                            "streetAddr": {
                                "stringValue": "13th Lenove St."
                            }
                        }
                    }
                },
                "cardDetails": {
                    "mapValue": {
                        "fields": {
                            "cardNum": {
                                "stringValue": "098765432123456"
                            },
                            "zipCode": {
                                "stringValue": "0123"
                            },
                            "cardName": {
                                "stringValue": "Gregg Gin"
                            },
                            "cardDate": {
                                "stringValue": "02/29"
                            }
                        }
                    }
                },
                "userId": {
                    "stringValue": "RItKmUrir2YPXDwrliwnQgxRMzj2"
                },
                "lastname": {
                    "stringValue": "Gin"
                },
                "imageName": {
                    "stringValue": "gregg@gmail.com1695894256585.jpeg"
                },
                "imageUrl": {
                    "stringValue": "https://firebasestorage.googleapis.com/v0/b/the-hidden-inn.appspot.com/o/oddUsers%2Fgregg%40gmail.com1695894256585.jpeg?alt=media&token=a7e89b00-bdcc-492d-9678-8c5b261a5a2a"
                },
                "phoneNum": {
                    "stringValue": "0897654321"
                }
            },
            "createTime": "2023-09-28T09:44:24.068403Z",
            "updateTime": "2023-10-03T07:30:47.094928Z"
        },
        {
            "name": "projects/the-hidden-inn/databases/(default)/documents/oddUsers/p5OgtzcL4Axh9OgJEVtD",
            "fields": {
                "cardDetails": {
                    "mapValue": {
                        "fields": {
                            "cardNum": {
                                "stringValue": "0123456789098765"
                            },
                            "cardName": {
                                "stringValue": "Roi Lyn"
                            },
                            "cardDate": {
                                "stringValue": "02/25"
                            },
                            "zipCode": {
                                "stringValue": "0123"
                            }
                        }
                    }
                },
                "emailAddress": {
                    "stringValue": "roi@yahoo.com"
                },
                "phoneNum": {
                    "stringValue": "0897654321"
                },
                "lastname": {
                    "stringValue": "Lyn"
                },
                "firstname": {
                    "stringValue": "Roi"
                },
                "imageName": {
                    "stringValue": "roi@yahoo.com1695892951092.jpeg"
                },
                "imageUrl": {
                    "stringValue": "https://firebasestorage.googleapis.com/v0/b/the-hidden-inn.appspot.com/o/oddUsers%2Froi%40yahoo.com1695892951092.jpeg?alt=media&token=232436bc-12e7-4bac-85b6-dd44594d8255"
                },
                "userId": {
                    "stringValue": "VN4NAftkApVdOSKbY3kILjQBeaG2"
                },
                "address": {
                    "mapValue": {
                        "fields": {
                            "city": {
                                "stringValue": "Groovy"
                            },
                            "streetAddr": {
                                "stringValue": "24th Ghost st."
                            },
                            "zipCode": {
                                "stringValue": "0123"
                            }
                        }
                    }
                }
            },
            "createTime": "2023-10-03T07:06:42.486497Z",
            "updateTime": "2023-10-03T07:06:42.486497Z"
        }
    ]
}